Workbook

Sheet Flujo Hosting
A1: Pimi — Flujo de fondos de hosting (Vercel + Supabase)
A2: Estimacion por etapa de crecimiento. Actualizar celdas azules a medida que cambien precios o supuestos.
A3: Fecha de referencia de precios: 19/07/2026 (Vercel y Supabase, sitios oficiales)
A5: Etapa | B5: Usuarios activos (MAU) — estimado | C5: Vercel: plan base | D5: Vercel: overage estimado | E5: Supabase: plan base | F5: Supabase: compute add-on | G5: Supabase: overage estimado | H5: Dominio (prorrateo mensual) | I5: Total mensual (USD) | J5: Total anual (USD)
A6: Etapa 0 — Lanzamiento / beta cerrada | B6: 300 | C6: 20 | D6: 0 | E6: 0 | F6: 0 | G6: 0 | H6: 1 | I6: =SUM(C6:H6) -> 21 | J6: =I6*12 -> 252
A7: Etapa 1 — Traccion inicial | B7: 3000 | C7: 20 | D7: 0 | E7: 25 | F7: 0 | G7: 0 | H7: 1 | I7: =SUM(C7:H7) -> 46 | J7: =I7*12 -> 552
A8: Etapa 2 — Buen crecimiento | B8: 20000 | C8: 20 | D8: 40 | E8: 25 | F8: 15 | G8: 15 | H8: 1 | I8: =SUM(C8:H8) -> 116 | J8: =I8*12 -> 1392
A9: Etapa 3 — Escala / mucho trafico | B9: 80000 | C9: 20 | D9: 180 | E9: 25 | F9: 60 | G9: 60 | H9: 1 | I9: =SUM(C9:H9) -> 346 | J9: =I9*12 -> 4152
A11: Supuestos y fuentes
A12: - Vercel Hobby (gratis) prohibe uso comercial en sus terminos -> Pimi necesita Pro ($20/mes por asiento) desde el lanzamiento.
A13: - Vercel Pro incluye $20 de credito de uso mensual; el overage solo aplica si el consumo real supera ese credito (fuente: vercel.com/pricing).
A14: - Supabase Free: 50.000 MAU, 500MB DB, 5GB egress, 1GB storage — pero el proyecto se pausa tras 7 dias de inactividad y no tiene backups. Sirve para Etapa 0 pero conviene pasar a Pro antes de tener usuarios reales pagando.
A15: - Supabase Pro: $25/mes (incluye credito de computo de $10, cubre instancia Micro), 100k MAU, 8GB DB, 250GB egress, backups diarios 7 dias (fuente: supabase.com/pricing).
A16: - Las columnas de 'overage estimado' en Etapas 2 y 3 son proyecciones aproximadas, no cotizaciones — el costo real depende del trafico, tamano de imagenes/paginas y uso de funciones server-side (middleware de Supabase SSR se ejecuta en cada request).
A17: - Dominio: prorrateo mensual aproximado de un dominio .com/.app (~$12-15/anio) — ajustar segun el TLD elegido.
A18: - No incluye: Mercado Pago (comisiones por transaccion, no es costo fijo), servicio de email transaccional si se agrega uno dedicado, ni herramientas de monitoreo/analytics de pago.

Sheet Apps Moviles
A1: Pimi — Costo de mantener las apps de iOS y Android
A2: Supuesto: apps construidas con Expo/React Native (reusa la logica del web), no nativas separadas. Si se desarrolla 100% nativo (Swift/Kotlin) estos costos de tooling son similares, pero el tiempo de desarrollo/mantenimiento humano (no incluido aca) es mucho mayor.
A3: Fecha de referencia de precios: 21/07/2026 (Apple, Google, Expo/EAS y Sentry, sitios oficiales)
A5: Etapa | B5: Apple Developer Program (prorrateo mensual) | C5: Google Play Console (prorrateo mensual) | D5: EAS Build / CI (compilacion iOS+Android) | E5: Monitoreo de errores (Sentry) | F5: Push notifications (Firebase FCM) | G5: Total mensual (USD) | H5: Total anual (USD)
A6: Etapa 0 — Lanzamiento / beta cerrada | B6: =99/12 -> 8.25 | C6: =25/12 -> 2.0833333 | D6: 0 | E6: 0 | F6: 0 | G6: =SUM(B6:F6) -> 10.333333 | H6: =G6*12 -> 124
A7: Etapa 1 — Traccion inicial | B7: =99/12 -> 8.25 | C7: 0 | D7: 0 | E7: 0 | F7: 0 | G7: =SUM(B7:F7) -> 8.25 | H7: =G7*12 -> 99
A8: Etapa 2 — Buen crecimiento | B8: =99/12 -> 8.25 | C8: 0 | D8: 19 | E8: 26 | F8: 0 | G8: =SUM(B8:F8) -> 53.25 | H8: =G8*12 -> 639
A9: Etapa 3 — Escala / mucho trafico | B9: =99/12 -> 8.25 | C9: 0 | D9: 199 | E9: 80 | F9: 0 | G9: =SUM(B9:F9) -> 287.25 | H9: =G9*12 -> 3447
A11: Supuestos y fuentes
A12: - Apple Developer Program: $99/anio, obligatorio para publicar y mantener la app en el App Store (fuente: developer.apple.com).
A13: - Google Play Console: $25 pago unico de por vida, no se renueva (fuente: play.google.com/console/about).
A14: - EAS Build (Expo): Free = 15 builds Android + 15 iOS por mes; Starter $19/mes ($45 credito de build); Production $199/mes ($225 credito) (fuente: expo.dev/pricing).
A15: - Sentry: Free = 5.000 errores/mes; Team $26/mes (50.000 errores); Business $80/mes (fuente: sentry.io/pricing).
A16: - Firebase Cloud Messaging (push notifications): gratis sin limite practico para este volumen de usuarios.
A17: - No incluye: tiempo de desarrollo/mantenimiento humano, diseno, ni el costo de una Mac si se compila localmente en vez de usar EAS Build en la nube (con EAS no hace falta tener Mac propia).
A18: - Si en cambio se elige no publicar apps nativas y quedarse con PWA (web instalable), este bloque completo se reduce a $0 -- opcion valida para el MVP inicial.

Sheet Resumen Total
A1: Pimi — Resumen consolidado: Hosting + Apps moviles
A2: Suma de la pestana 'Flujo Hosting' + 'Apps Moviles' por etapa. Los valores se recalculan solos si cambian las otras pestanas.
A4: Etapa | B4: Total Hosting (mensual) | C4: Total Apps Moviles (mensual) | D4: Total consolidado (mensual) | E4: Total consolidado (anual)
A5: Etapa 0 — Lanzamiento / beta cerrada | B5: ='Flujo Hosting'!I6 -> 21 | C5: ='Apps Moviles'!G6 -> 10.333333 | D5: =B5+C5 -> 31.333333 | E5: =D5*12 -> 376
A6: Etapa 1 — Traccion inicial | B6: ='Flujo Hosting'!I7 -> 46 | C6: ='Apps Moviles'!G7 -> 8.25 | D6: =B6+C6 -> 54.25 | E6: =D6*12 -> 651
A7: Etapa 2 — Buen crecimiento | B7: ='Flujo Hosting'!I8 -> 116 | C7: ='Apps Moviles'!G8 -> 53.25 | D7: =B7+C7 -> 169.25 | E7: =D7*12 -> 2031
A8: Etapa 3 — Escala / mucho trafico | B8: ='Flujo Hosting'!I9 -> 346 | C8: ='Apps Moviles'!G9 -> 287.25 | D8: =B8+C8 -> 633.25 | E8: =D8*12 -> 7599
A10: Nota: no incluye comision de Mercado Pago (variable por transaccion) ni tiempo de desarrollo/mantenimiento humano de ninguna de las dos plataformas.
